inpass/__init__.py
inpass/cli.py
inpass/core.py
inpass-2.0.0.dist-info/LICENSE
inpass-2.0.0.dist-info/METADATA
inpass-2.0.0.dist-info/WHEEL
inpass-2.0.0.dist-info/entry_points.txt
inpass-2.0.0.dist-info/top_level.txt
inpass-2.0.0.dist-info/RECORD
