Metadata-Version: 2.1
Name: inpass
Version: 2.0.0
Summary: Automated login attempts for Instagram.
Home-page: https://mrfidal.in
Author: Fidal
Author-email: mrfidal@proton.me
License-File: LICENSE
